README.rst
setup.py
datanorth/__init__.py
datanorth/datanorth.py
datanorth/version.py
datanorth.egg-info/PKG-INFO
datanorth.egg-info/SOURCES.txt
datanorth.egg-info/dependency_links.txt
datanorth.egg-info/requires.txt
datanorth.egg-info/top_level.txt
datanorth.egg-info/zip-safe