Metadata-Version: 1.0
Name: datanorth
Version: 0.0.0
Summary: Python client for the DataNorth API.
Home-page: https://github.com/data-north/datanorth-python
Author: Jason Haas
Author-email: jasonrhaas@gmail.com
License: MIT
Keywords: datanorth,api,python
Platform: UNKNOWN
